JsonLLM/__init__.py
JsonLLM/jllm.py
jsonLiteLLM-1.0.0.dist-info/METADATA
jsonLiteLLM-1.0.0.dist-info/WHEEL
jsonLiteLLM-1.0.0.dist-info/top_level.txt
jsonLiteLLM-1.0.0.dist-info/RECORD
